dij/__init__.py
dij/container.py
dij/exception.py
dij/resolver/__init__.py
dij/resolver/context.py
dij/resolver/dynamic.py
dij/resolver/factory.py
dij/resolver/factory_async.py
dij/resolver/instance.py
dij/resolver/singleton.py
dij/resolver/type.py
dij/svc.py
dij/types.py
dij/utils.py
dij-0.0.6.dist-info/LICENSE
dij-0.0.6.dist-info/METADATA
dij-0.0.6.dist-info/WHEEL
dij-0.0.6.dist-info/RECORD
