Metadata-Version: 2.3
Name: dij
Version: 0.0.6
Summary: 💉 dij » dependency dijection library
License: MIT
Keywords: dependency,injection,di
Author: Lucas Colombo
Author-email: lucas@lucode.dev
Requires-Python: >=3.9,<4.0
Classifier: Development Status :: 5 - Production/Stable
Classifier: License :: OSI Approved :: MIT License
Classifier: Programming Language :: Python :: 3
Classifier: Programming Language :: Python :: 3.9
Classifier: Programming Language :: Python :: 3.10
Classifier: Programming Language :: Python :: 3.11
Classifier: Programming Language :: Python :: 3.12
Classifier: Programming Language :: Python :: 3.13
Classifier: Operating System :: OS Independent
Classifier: Topic :: Software Development :: Libraries
Requires-Dist: requests (>=2.32.3,<3.0.0)
Requires-Dist: typing-extensions (>=4.12.2,<5.0.0)
Project-URL: Bug Tracker, https://github.com/lucodear/dij/issues
Project-URL: Documentation, https://github.com/lucodear/dij#readme
Project-URL: Homepage, https://github.com/lucodear/dij
Project-URL: Repository, https://github.com/lucodear/dij
